[1,["eewfW4s0pHBoGxLLW+x65W@6c48a"],["_textureSource"],["cc.SpriteFrame"],0,[{"name":"gj10","rect":{"x":5,"y":3,"width":122,"height":122},"offset":{"x":2,"y":0},"originalSize":{"width":128,"height":128},"rotated":false,"capInsets":[0,0,0,0],"vertices":{"rawPosition":[-61,-61,0,61,-61,0,-61,61,0,61,61,0],"indexes":[0,1,2,2,1,3],"uv":[5,125,127,125,5,3,127,3],"nuv":[0.0390625,0.0234375,0.9921875,0.0234375,0.0390625,0.9765625,0.9921875,0.9765625],"minPos":{"x":-61,"y":-61,"z":0},"maxPos":{"x":61,"y":61,"z":0}},"packable":true,"pixelsToUnit":100,"pivot":{"x":0.5,"y":0.5},"meshType":0}],[0],0,[0],[0],[0]]
