[1,["66QEusX29NwYyUBQmQOlbB@6c48a"],0,[["sp.SkeletonData",["_name","_atlasText","textureNames","_skeletonJson","textures"],-1,3]],[[0,0,1,2,3,4,5]],[[0,"buff_fire","\nbuff_fire.png\nsize: 378,322\nformat: RGBA8888\nfilter: Linear,Linear\nrepeat: none\n000\n  rotate: true\n  xy: 92, 97\n  size: 223, 100\n  orig: 223, 100\n  offset: 0, 0\n  index: -1\n001\n  rotate: false\n  xy: 2, 2\n  size: 221, 92\n  orig: 221, 92\n  offset: 0, 0\n  index: -1\n002\n  rotate: true\n  xy: 194, 98\n  size: 222, 90\n  orig: 222, 90\n  offset: 0, 0\n  index: -1\n003\n  rotate: true\n  xy: 286, 99\n  size: 221, 90\n  orig: 221, 90\n  offset: 0, 0\n  index: -1\n004\n  rotate: true\n  xy: 2, 96\n  size: 224, 88\n  orig: 224, 88\n  offset: 0, 0\n  index: -1\n",["buff_fire.png"],{"skeleton":{"hash":"hFehSAI/6kuPO5wPqsX7P2xDPyY","spine":"2.1.27","width":221,"height":90,"images":""},"bones":[{"name":"root"},{"name":"bone","parent":"root","length":89.99,"rotation":180}],"slots":[{"name":"000","bone":"bone","attachment":"003"}],"skins":{"default":{"000":{"000":{"x":-1.81,"y":6.51,"rotation":-180,"width":223,"height":100},"001":{"x":-1.29,"y":0.87,"rotation":-180,"width":221,"height":92},"002":{"x":-1.4,"y":0.22,"rotation":-180,"width":222,"height":90},"003":{"x":-0.99,"y":0.53,"rotation":-180,"width":221,"height":90},"004":{"x":-2.72,"y":0.84,"rotation":-180,"width":224,"height":88}}}},"animations":{"animation":{"slots":{"000":{"attachment":[{"time":0,"name":"000"},{"time":0.0666,"name":"001"},{"time":0.1333,"name":"002"},{"time":0.2,"name":"003"},{"time":0.2666,"name":"004"}]}},"bones":{"bone":{"rotate":[{"time":0,"angle":0,"curve":"stepped"},{"time":0.2666,"angle":0}],"translate":[{"time":0,"x":0,"y":0,"curve":"stepped"},{"time":0.2666,"x":0,"y":0}],"scale":[{"time":0,"x":1,"y":1,"curve":"stepped"},{"time":0.2666,"x":1,"y":1}]}}}}},[0]]],0,0,[0],[-1],[0]]
