[1,["90Ih0xJsxNs5sXXvPMriwS@6c48a"],["_textureSource"],["cc.SpriteFrame"],0,[{"name":"sword","rect":{"x":68,"y":4,"width":65,"height":190},"offset":{"x":0.5,"y":1},"originalSize":{"width":200,"height":200},"rotated":false,"capInsets":[0,0,0,0],"vertices":{"rawPosition":[-32.5,-95,0,32.5,-95,0,-32.5,95,0,32.5,95,0],"indexes":[0,1,2,2,1,3],"uv":[68,196,133,196,68,6,133,6],"nuv":[0.34,0.03,0.665,0.03,0.34,0.98,0.665,0.98],"minPos":{"x":-32.5,"y":-95,"z":0},"maxPos":{"x":32.5,"y":95,"z":0}},"packable":true,"pixelsToUnit":100,"pivot":{"x":0.5,"y":0.5},"meshType":0}],[0],0,[0],[0],[0]]
